base_utils/__init__.py
base_utils/dtos.py
base_utils/error_types.py
base_utils/exception.py
base_utils/service.py
base_utils/utils.py
broker/__init__.py
broker/rabbitmq.py
database/__init__.py
database/mongodb.py
database/redis.py
closehaven_abc-0.1.14.dist-info/METADATA
closehaven_abc-0.1.14.dist-info/WHEEL
closehaven_abc-0.1.14.dist-info/top_level.txt
closehaven_abc-0.1.14.dist-info/RECORD
