Metadata-Version: 2.1
Name: closehaven-abc
Version: 0.1.14
Summary: UNKNOWN
Home-page: UNKNOWN
Author: UNKNOWN
Author-email: UNKNOWN
License: UNKNOWN
Platform: UNKNOWN
Requires-Dist: fastapi==0.115.0
Requires-Dist: pydantic==2.9.2
Requires-Dist: azure-storage-blob==12.23.0
Requires-Dist: certifi==2024.8.30
Requires-Dist: beanie==1.26.0
Requires-Dist: motor==3.6.0
Requires-Dist: aio-pika==9.4.3
Requires-Dist: async-timeout==4.0.3
Requires-Dist: pyjwt==2.9.0
Requires-Dist: uvloop==0.20.0
Requires-Dist: redis==5.0.8
